{"note":"This file is an internal implementation detail to speed up HTML report generation. Its format can change at any time. You might be looking for the JSON report: https://coverage.rtfd.io/cmd.html#cmd-json","format":2,"version":"7.4.4","globals":"f611eb9b04e7d5fed8d0af0752d8c54a","files":{"d_145eef247bfb46b6_chart_py":{"hash":"a7434ce97a7a756a4ee863faf01c4b4b","index":{"nums":[0,1,39,0,4,0,0,0],"html_filename":"d_145eef247bfb46b6_chart_py.html","relative_filename":"src/chart.py"}},"d_145eef247bfb46b6_tcx_py":{"hash":"8c5689858c0763105b93ebfb0e7434ac","index":{"nums":[0,1,66,0,1,0,0,0],"html_filename":"d_145eef247bfb46b6_tcx_py.html","relative_filename":"src/tcx.py"}}}}